file_manager/__init__.py
file_manager/create_folder.py
file_manager/filtered_tree.py
file_manager/main.css
file_manager/main.py
file_manager/rename_modal.py
n_filej-0.1.8.dist-info/METADATA
n_filej-0.1.8.dist-info/WHEEL
n_filej-0.1.8.dist-info/entry_points.txt
n_filej-0.1.8.dist-info/licenses/LICENSE
n_filej-0.1.8.dist-info/RECORD
