Metadata-Version: 2.4
Name: n-filej
Version: 0.1.8
Summary: A simple, TUI-based file manager written in Python using Textual.
Author-email: NJ Mahir <njprograms29@gmail.com>
License: GPL-3.0-only
License-File: LICENSE
Keywords: file-manager,terminal,textual,tui
Requires-Python: >=3.11
Requires-Dist: pyperclip>=1.11.0
Requires-Dist: rich>=14.2.0
Requires-Dist: textual>=6.11.0
